moon_manager/__init__.py
moon_manager/__main__.py
moon_manager/daemon.py
moon_manager/db_driver.py
moon_manager/manager_setup.py
moon_manager/orchestration_driver.py
moon_manager/pip_driver.py
moon_manager/server.py
moon_manager/api/__init__.py
moon_manager/api/assignments.py
moon_manager/api/attributes.py
moon_manager/api/auth.py
moon_manager/api/checks.py
moon_manager/api/configuration.py
moon_manager/api/data.py
moon_manager/api/json_export.py
moon_manager/api/json_import.py
moon_manager/api/logs.py
moon_manager/api/meta_data.py
moon_manager/api/meta_rules.py
moon_manager/api/models.py
moon_manager/api/pdp.py
moon_manager/api/perimeter.py
moon_manager/api/policy.py
moon_manager/api/rules.py
moon_manager/api/slave.py
moon_manager/api/status.py
moon_manager/api/users.py
moon_manager/api/db/__init__.py
moon_manager/api/db/managers.py
moon_manager/api/db/model.py
moon_manager/api/db/pdp.py
moon_manager/api/db/policy.py
moon_manager/api/db/slave.py
moon_manager/api/db/migrations/__init__.py
moon_manager/api/db/migrations/moon_001.py
moon_manager/api/information/__init__.py
moon_manager/api/information/global_attrs.py
moon_manager/api/information/information.py
moon_manager/api/information/managers.py
moon_manager/api/orchestration/__init__.py
moon_manager/api/orchestration/managers.py
moon_manager/api/orchestration/pipeline.py
moon_manager/api/orchestration/slave.py
moon_manager/plugins/__init__.py
moon_manager/plugins/global_attrs.py
moon_manager/plugins/moon_keystone_plugin.py
moon_manager/plugins/moon_nova_plugin.py
moon_manager/plugins/moon_openstack_plugin.py
moon_manager/plugins/pyorchestrator.py
moon_manager/plugins/sql.py
moon_manager-0.9.1.data/data/moon/moon.yaml
moon_manager-0.9.1.data/data/moon/moonrc
moon_manager-0.9.1.dist-info/LICENSE
moon_manager-0.9.1.dist-info/METADATA
moon_manager-0.9.1.dist-info/WHEEL
moon_manager-0.9.1.dist-info/entry_points.txt
moon_manager-0.9.1.dist-info/top_level.txt
moon_manager-0.9.1.dist-info/RECORD
