Metadata-Version: 2.1
Name: moon-manager
Version: 0.9.1
Summary: UNKNOWN
Home-page: UNKNOWN
Author: Thomas Duval
Author-email: thomas.duval@orange.com
License: UNKNOWN
Platform: UNKNOWN
Classifier: Programming Language :: Python
Classifier: Development Status :: 1 - Planning
Classifier: License :: OSI Approved
Classifier: Natural Language :: French
Classifier: Operating System :: OS Independent
Classifier: Programming Language :: Python :: 3
Requires-Dist: hug (!=2.5.0)
Requires-Dist: pyyaml
Requires-Dist: moon-utilities
Requires-Dist: moon-engine
Requires-Dist: tinydb
Requires-Dist: gunicorn
Requires-Dist: requests
Requires-Dist: sqlalchemy
Requires-Dist: pymysql
